[
  {
    "id": 19,
    "title": "Smart Home",
    "catIng": "",
    "products": [
      {
        "id": 3,
        "name": "N-5100",
        "brandCode": "222",
        "realPrice": 45000,
        "buyPrice": 46000,
        "agentCommission": null,
        "img": "[\"23-1647954790814.jpg\"]",
        "shortDescription": "good quality",
        "fullDescription": "better performance",
        "userId": 11,
        "productOwner": "Admin",
        "status": "Offer",
        "productType": "Reguler",
        "offerAmount": null,
        "discountAmount": 1000,
        "cashBackAmount": 2000,
        "productDeliveryCharge": 120,
        "chk": 0,
        "date": "2022-03-22"
      },
      {
        "id": 4,
        "name": "N-5200",
        "brandCode": "222",
        "realPrice": 55000,
        "buyPrice": 56000,
        "agentCommission": null,
        "img": "[\"photo-1516724562728-afc824a36e84-1647954867264.jfif\"]",
        "shortDescription": "good quality",
        "fullDescription": "better performance",
        "userId": 11,
        "productOwner": "Admin",
        "status": "Offer",
        "productType": "Reguler",
        "offerAmount": null,
        "discountAmount": 1000,
        "cashBackAmount": 2000,
        "productDeliveryCharge": 120,
        "chk": 0,
        "date": "2022-03-22"
      },
      {
        "id": 5,
        "name": "N-5400",
        "brandCode": "222",
        "realPrice": 35000,
        "buyPrice": 36000,
        "agentCommission": null,
        "img": "[\"7-1647954941322.jpg\"]",
        "shortDescription": "good quality",
        "fullDescription": "better performance",
        "userId": 11,
        "productOwner": "Admin",
        "status": "FlashSales",
        "productType": "Reguler",
        "offerAmount": null,
        "discountAmount": 1000,
        "cashBackAmount": 2000,
        "productDeliveryCharge": 120,
        "chk": 1,
        "date": "2022-03-22"
      },
      {
        "id": 22,
        "name": "ss",
        "brandCode": "212",
        "realPrice": 20000,
        "buyPrice": 22000,
        "agentCommission": null,
        "img": "[\"1576723928-5230-1648592981730.png\"]",
        "shortDescription": "sss",
        "fullDescription": "ss",
        "userId": 11,
        "productOwner": "Admin",
        "status": "Reguler",
        "productType": "Package",
        "offerAmount": null,
        "discountAmount": 200,
        "cashBackAmount": 500,
        "productDeliveryCharge": 120,
        "chk": 1,
        "date": "2022-03-30"
      },
      {
        "id": 23,
        "name": "ss",
        "brandCode": "212",
        "realPrice": 20000,
        "buyPrice": 22000,
        "agentCommission": null,
        "img": "[\"1576723928-5230-1648594555367.png\"]",
        "shortDescription": "sss",
        "fullDescription": "ss",
        "userId": 11,
        "productOwner": "Admin",
        "status": "Reguler",
        "productType": "Package",
        "offerAmount": null,
        "discountAmount": 200,
        "cashBackAmount": 500,
        "productDeliveryCharge": 120,
        "chk": 1,
        "date": "2022-03-30"
      }
    ]
  },
  {
    "id": 18,
    "title": "Women's Fashion",
    "catIng": "",
    "products": [
      {
        "id": 9,
        "name": "Apple",
        "brandCode": "221",
        "realPrice": 430,
        "buyPrice": 440,
        "agentCommission": null,
        "img": "[\"34-1647955441958.jpg\"]",
        "shortDescription": "good",
        "fullDescription": "quality better",
        "userId": 11,
        "productOwner": "Admin",
        "status": "Offer",
        "productType": "Reguler",
        "offerAmount": null,
        "discountAmount": 30,
        "cashBackAmount": 12,
        "productDeliveryCharge": 50,
        "chk": 1,
        "date": "2022-03-22"
      },
      {
        "id": 10,
        "name": "Apple",
        "brandCode": "221",
        "realPrice": 500,
        "buyPrice": 550,
        "agentCommission": null,
        "img": "[\"17-1647955457117.jpg\"]",
        "shortDescription": "good",
        "fullDescription": "quality better",
        "userId": 11,
        "productOwner": "Admin",
        "status": "Offer",
        "productType": "Reguler",
        "offerAmount": null,
        "discountAmount": 30,
        "cashBackAmount": 12,
        "productDeliveryCharge": 50,
        "chk": 0,
        "date": "2022-03-22"
      },
      {
        "id": 11,
        "name": "Apple",
        "brandCode": "221",
        "realPrice": 400,
        "buyPrice": 440,
        "agentCommission": null,
        "img": "[\"photo-1593121925328-369cc8459c08-1647955476522.jfif\"]",
        "shortDescription": "good",
        "fullDescription": "quality better",
        "userId": 11,
        "productOwner": "Admin",
        "status": "FlashSales",
        "productType": "Reguler",
        "offerAmount": null,
        "discountAmount": 30,
        "cashBackAmount": 12,
        "productDeliveryCharge": 50,
        "chk": 1,
        "date": "2022-03-22"
      },
      {
        "id": 12,
        "name": "Apple",
        "brandCode": "221",
        "realPrice": 400,
        "buyPrice": 440,
        "agentCommission": null,
        "img": "[\"photo-1574494461754-de04dc403eec-1647955516530.jfif\"]",
        "shortDescription": "good",
        "fullDescription": "quality better",
        "userId": 11,
        "productOwner": "Admin",
        "status": "FlashSales",
        "productType": "Reguler",
        "offerAmount": null,
        "discountAmount": 30,
        "cashBackAmount": 12,
        "productDeliveryCharge": 50,
        "chk": 0,
        "date": "2022-03-22"
      },
      {
        "id": 13,
        "name": "Apple",
        "brandCode": "221",
        "realPrice": 400,
        "buyPrice": 440,
        "agentCommission": null,
        "img": "[\"photo-1612444530582-fc66183b16f7-1647955524924.jfif\"]",
        "shortDescription": "good",
        "fullDescription": "quality better",
        "userId": 11,
        "productOwner": "Admin",
        "status": "FlashSales",
        "productType": "Reguler",
        "offerAmount": null,
        "discountAmount": 30,
        "cashBackAmount": 12,
        "productDeliveryCharge": 50,
        "chk": 0,
        "date": "2022-03-22"
      },
      {
        "id": 14,
        "name": "Apple",
        "brandCode": "221",
        "realPrice": 400,
        "buyPrice": 440,
        "agentCommission": null,
        "img": "[\"photo-1610041321327-b794c052db27-1647955534158.jfif\"]",
        "shortDescription": "good",
        "fullDescription": "quality better",
        "userId": 11,
        "productOwner": "Admin",
        "status": "FlashSales",
        "productType": "Reguler",
        "offerAmount": null,
        "discountAmount": 30,
        "cashBackAmount": 12,
        "productDeliveryCharge": 50,
        "chk": 1,
        "date": "2022-03-22"
      },
      {
        "id": 15,
        "name": "Apple",
        "brandCode": "221",
        "realPrice": 400,
        "buyPrice": 440,
        "agentCommission": null,
        "img": "[\"38-1647955557904.jpg\"]",
        "shortDescription": "good",
        "fullDescription": "quality better",
        "userId": 11,
        "productOwner": "Admin",
        "status": "FlashSales",
        "productType": "Reguler",
        "offerAmount": null,
        "discountAmount": 30,
        "cashBackAmount": 12,
        "productDeliveryCharge": 50,
        "chk": 1,
        "date": "2022-03-22"
      },
      {
        "id": 25,
        "name": "Apple",
        "brandCode": "312",
        "realPrice": 430,
        "buyPrice": 440,
        "agentCommission": null,
        "img": "[\"photo-1613040809024-b4ef7ba99bc3-1649062520282.jfif\"]",
        "shortDescription": "ssd",
        "fullDescription": "dddddddddddddwe",
        "userId": 11,
        "productOwner": "Admin",
        "status": "Offer",
        "productType": "Reguler",
        "offerAmount": null,
        "discountAmount": 30,
        "cashBackAmount": 20,
        "productDeliveryCharge": 50,
        "chk": 1,
        "date": "2022-04-04"
      }
    ]
  },
  {
    "id": 17,
    "title": "Pet supplies",
    "catIng": "",
    "products": [
      {
        "id": 4,
        "name": "Apple",
        "brandCode": "221",
        "realPrice": 60002,
        "buyPrice": 66666,
        "agentCommission": null,
        "img": "[\"31-1647955684219.jpg\"]",
        "shortDescription": "good",
        "fullDescription": "quality better",
        "userId": 11,
        "productOwner": "Admin",
        "status": "FlashSales",
        "productType": "Reguler",
        "offerAmount": null,
        "discountAmount": 30,
        "cashBackAmount": 12,
        "productDeliveryCharge": 50,
        "chk": 1,
        "date": "2022-03-22"
      },
      {
        "id": 20,
        "name": "Apple",
        "brandCode": "221",
        "realPrice": 60002,
        "buyPrice": 66666,
        "agentCommission": null,
        "img": "[\"photo-1496917798719-b3d55924118d-1647955698183.jfif\"]",
        "shortDescription": "good",
        "fullDescription": "quality better",
        "userId": 11,
        "productOwner": "Admin",
        "status": "FlashSales",
        "productType": "Reguler",
        "offerAmount": null,
        "discountAmount": 30,
        "cashBackAmount": 12,
        "productDeliveryCharge": 50,
        "chk": 0,
        "date": "2022-03-22"
      }
    ]
  },
  {
    "id": 16,
    "title": "Video games",
    "catIng": "",
    "products": [
      {
        "id": 16,
        "name": "Apple",
        "brandCode": "221",
        "realPrice": 400,
        "buyPrice": 440,
        "agentCommission": null,
        "img": "[\"6-1647955605813.jpg\"]",
        "shortDescription": "good",
        "fullDescription": "quality better",
        "userId": 11,
        "productOwner": "Admin",
        "status": "FlashSales",
        "productType": "Reguler",
        "offerAmount": null,
        "discountAmount": 30,
        "cashBackAmount": 12,
        "productDeliveryCharge": 50,
        "chk": 1,
        "date": "2022-03-22"
      },
      {
        "id": 17,
        "name": "Apple",
        "brandCode": "221",
        "realPrice": 400,
        "buyPrice": 440,
        "agentCommission": null,
        "img": "[\"18-1647955615985.jpg\"]",
        "shortDescription": "good",
        "fullDescription": "quality better",
        "userId": 11,
        "productOwner": "Admin",
        "status": "FlashSales",
        "productType": "Reguler",
        "offerAmount": null,
        "discountAmount": 30,
        "cashBackAmount": 12,
        "productDeliveryCharge": 50,
        "chk": 1,
        "date": "2022-03-22"
      },
      {
        "id": 18,
        "name": "Apple",
        "brandCode": "221",
        "realPrice": 220,
        "buyPrice": 222,
        "agentCommission": null,
        "img": "[\"37-1647955631256.jpg\"]",
        "shortDescription": "good",
        "fullDescription": "quality better",
        "userId": 11,
        "productOwner": "Admin",
        "status": "FlashSales",
        "productType": "Reguler",
        "offerAmount": null,
        "discountAmount": 30,
        "cashBackAmount": 12,
        "productDeliveryCharge": 50,
        "chk": 1,
        "date": "2022-03-22"
      },
      {
        "id": 28,
        "name": "APPLE-21",
        "brandCode": "312",
        "realPrice": 430,
        "buyPrice": 440,
        "agentCommission": null,
        "img": "[\"photo-1545127398-14699f92334b-1649062699510.jfif\"]",
        "shortDescription": "ssd",
        "fullDescription": "dddddddddddddwe",
        "userId": 11,
        "productOwner": "Admin",
        "status": "Offer",
        "productType": "Reguler",
        "offerAmount": null,
        "discountAmount": 30,
        "cashBackAmount": 20,
        "productDeliveryCharge": 50,
        "chk": 0,
        "date": "2022-04-04"
      }
    ]
  },
  {
    "id": 21,
    "title": "Camera",
    "catIng": "",
    "products": [
      {
        "id": 6,
        "name": "B-100",
        "brandCode": "12",
        "realPrice": 2000,
        "buyPrice": 2200,
        "agentCommission": null,
        "img": "[\"10-1647955040234.jpg\"]",
        "shortDescription": "good quality",
        "fullDescription": "better performance",
        "userId": 11,
        "productOwner": "Admin",
        "status": "FlashSales",
        "productType": "Reguler",
        "offerAmount": null,
        "discountAmount": 111,
        "cashBackAmount": 120,
        "productDeliveryCharge": 120,
        "chk": 1,
        "date": "2022-03-22"
      },
      {
        "id": 7,
        "name": "B-100",
        "brandCode": "12",
        "realPrice": 2500,
        "buyPrice": 2600,
        "agentCommission": null,
        "img": "[\"photo-1560769629-975ec94e6a86-1647955071532.jfif\"]",
        "shortDescription": "good quality",
        "fullDescription": "better performance",
        "userId": 11,
        "productOwner": "Admin",
        "status": "FlashSales",
        "productType": "Reguler",
        "offerAmount": null,
        "discountAmount": 111,
        "cashBackAmount": 120,
        "productDeliveryCharge": 120,
        "chk": 1,
        "date": "2022-03-22"
      },
      {
        "id": 8,
        "name": "C-100",
        "brandCode": "12",
        "realPrice": 2500,
        "buyPrice": 2600,
        "agentCommission": null,
        "img": "[\"photo-1595950653106-6c9ebd614d3a-1647955094771.jfif\"]",
        "shortDescription": "good quality",
        "fullDescription": "better performance",
        "userId": 11,
        "productOwner": "Admin",
        "status": "Reguler",
        "productType": "Reguler",
        "offerAmount": null,
        "discountAmount": 111,
        "cashBackAmount": 120,
        "productDeliveryCharge": 120,
        "chk": 1,
        "date": "2022-03-22"
      },
      {
        "id": 24,
        "name": "Xiomi",
        "brandCode": "216",
        "realPrice": 2222,
        "buyPrice": 1800,
        "agentCommission": null,
        "img": "[\"2-1648716892820.jpg\"]",
        "shortDescription": "skjdhir",
        "fullDescription": "oewrrgtoogo",
        "userId": 11,
        "productOwner": "Admin",
        "status": "Reguler",
        "productType": "Package",
        "offerAmount": null,
        "discountAmount": 30,
        "cashBackAmount": 20,
        "productDeliveryCharge": 50,
        "chk": 1,
        "date": "2022-03-31"
      }
    ]
  },
  {
    "id": 31,
    "title": "Computer",
    "catIng": "",
    "products": [
      {
        "id": 6,
        "name": "B-100",
        "brandCode": "12",
        "realPrice": 2000,
        "buyPrice": 2200,
        "agentCommission": null,
        "img": "[\"10-1647955040234.jpg\"]",
        "shortDescription": "good quality",
        "fullDescription": "better performance",
        "userId": 11,
        "productOwner": "Admin",
        "status": "FlashSales",
        "productType": "Reguler",
        "offerAmount": null,
        "discountAmount": 111,
        "cashBackAmount": 120,
        "productDeliveryCharge": 120,
        "chk": 1,
        "date": "2022-03-22"
      },
      {
        "id": 7,
        "name": "B-100",
        "brandCode": "12",
        "realPrice": 2500,
        "buyPrice": 2600,
        "agentCommission": null,
        "img": "[\"photo-1560769629-975ec94e6a86-1647955071532.jfif\"]",
        "shortDescription": "good quality",
        "fullDescription": "better performance",
        "userId": 11,
        "productOwner": "Admin",
        "status": "FlashSales",
        "productType": "Reguler",
        "offerAmount": null,
        "discountAmount": 111,
        "cashBackAmount": 120,
        "productDeliveryCharge": 120,
        "chk": 1,
        "date": "2022-03-22"
      },
      {
        "id": 8,
        "name": "C-100",
        "brandCode": "12",
        "realPrice": 2500,
        "buyPrice": 2600,
        "agentCommission": null,
        "img": "[\"photo-1595950653106-6c9ebd614d3a-1647955094771.jfif\"]",
        "shortDescription": "good quality",
        "fullDescription": "better performance",
        "userId": 11,
        "productOwner": "Admin",
        "status": "Reguler",
        "productType": "Reguler",
        "offerAmount": null,
        "discountAmount": 111,
        "cashBackAmount": 120,
        "productDeliveryCharge": 120,
        "chk": 1,
        "date": "2022-03-22"
      },
      {
        "id": 24,
        "name": "Xiomi",
        "brandCode": "216",
        "realPrice": 2222,
        "buyPrice": 1800,
        "agentCommission": null,
        "img": "[\"2-1648716892820.jpg\"]",
        "shortDescription": "skjdhir",
        "fullDescription": "oewrrgtoogo",
        "userId": 11,
        "productOwner": "Admin",
        "status": "Reguler",
        "productType": "Package",
        "offerAmount": null,
        "discountAmount": 30,
        "cashBackAmount": 20,
        "productDeliveryCharge": 50,
        "chk": 1,
        "date": "2022-03-31"
      }
    ]
  },
  {
    "id": 21,
    "title": "Food",
    "catIng": "",
    "products": [
      {
        "id": 6,
        "name": "Pasta",
        "code": "12",
        "price": 200,
        "size": "large",
        "img": "[\"10-1647955040234.jpg\"]",
        "shortDescription": "good quality",
        "fullDescription": "better performance",
        "status": "FlashSales",
        "productType": "Reguler",
        "date": "2022-03-22"
      },
      {
        "id": 9,
        "name": "Burger",
        "code": "13",
        "price": 200,
        "size": "large",
        "img": "[\"10-1647955040234.jpg\"]",
        "shortDescription": "good quality",
        "fullDescription": "better performance",
        "status": "FlashSales",
        "productType": "Reguler",
        "date": "2022-03-22"
      },
      {
        "id": 6,
        "name": "Pasta",
        "code": "12",
        "price": 200,
        "size": "large",
        "img": "[\"10-1647955040234.jpg\"]",
        "shortDescription": "good quality",
        "fullDescription": "better performance",
        "status": "FlashSales",
        "productType": "Reguler",
        "date": "2022-03-22"
      },
      {
        "id": 9,
        "name": "Burger",
        "code": "13",
        "price": 200,
        "size": "large",
        "img": "[\"10-1647955040234.jpg\"]",
        "shortDescription": "good quality",
        "fullDescription": "better performance",
        "status": "FlashSales",
        "productType": "Reguler",
        "date": "2022-03-22"
      }
    ]
  }
]
